imgedit/__init__.py
imgedit/common/__init__.py
imgedit/common/types/__init__.py
imgedit/common/types/image_format.py
imgedit/common/types/pil_color.py
imgedit/common/utils/__init__.py
imgedit/common/utils/image_format.py
imgedit/crop/__init__.py
imgedit/crop/crop.py
imgedit/imgedit.egg-info/PKG-INFO
imgedit/imgedit.egg-info/SOURCES.txt
imgedit/imgedit.egg-info/dependency_links.txt
imgedit/imgedit.egg-info/requires.txt
imgedit/imgedit.egg-info/top_level.txt
imgedit/resize/__init__.py
imgedit/resize/resize.py
imgedit-0.1.1.dist-info/licenses/LICENSE
imgedit-0.1.1.dist-info/METADATA
imgedit-0.1.1.dist-info/WHEEL
imgedit-0.1.1.dist-info/top_level.txt
imgedit-0.1.1.dist-info/RECORD
