Metadata-Version: 2.4
Name: imgedit
Version: 0.1.1
Summary: A small Python library for editing images
Home-page: https://github.com/kkristof200/py_img_edit
Author: Kovács Kristóf-Attila
License: MIT License
Project-URL: Homepage, https://github.com/kkristof200/py_img_edit
Project-URL: Repository, https://github.com/kkristof200/py_img_edit
Project-URL: Issues, https://github.com/kkristof200/py_img_edit/issues
Keywords: image,editing,resize,pillow,graphics
Classifier: Development Status :: 3 - Alpha
Classifier: Intended Audience :: Developers
Classifier: License :: OSI Approved :: MIT License
Classifier: Operating System :: OS Independent
Classifier: Topic :: Multimedia :: Graphics
Classifier: Programming Language :: Python :: 3
Classifier: Programming Language :: Python :: 3.8
Classifier: Programming Language :: Python :: 3.9
Classifier: Programming Language :: Python :: 3.10
Classifier: Programming Language :: Python :: 3.11
Classifier: Programming Language :: Python :: 3.12
Requires-Python: >=3.8
License-File: LICENSE
Requires-Dist: pillow>=11.3.0
Provides-Extra: dev
Requires-Dist: pytest>=8.0.0; extra == "dev"
Requires-Dist: ruff>=0.4.0; extra == "dev"
Requires-Dist: mypy>=1.10.0; extra == "dev"
Requires-Dist: build>=1.2.0; extra == "dev"
Requires-Dist: twine>=5.0.0; extra == "dev"
Dynamic: home-page
Dynamic: license-file
Dynamic: requires-python
